th/__init__.py
th/_error.py
th/_path_holder.py
th/_path_holder_proxy.py
th/_version.py
th/py.typed
th/operators/__init__.py
th/operators/_operator.py
th-0.4.1.dist-info/LICENSE.txt
th-0.4.1.dist-info/METADATA
th-0.4.1.dist-info/WHEEL
th-0.4.1.dist-info/top_level.txt
th-0.4.1.dist-info/RECORD
